MANIFEST.in
README.txt
setup.cfg
setup.py
docs/HISTORY.txt
docs/Makefile
docs/ambiente.txt
docs/boaspraticas.txt
docs/conf.py
docs/configuracao.txt
docs/index.txt
docs/introducao.txt
docs/make.bat
docs/pacotes.txt
docs/releases.txt
docs/_static/simples.css
docs/_static/simples.gif
docs/_templates/page.html
docs/_templates/simples.css
docs/vcs/index.txt
docs/vcs/mercurial.txt
docs/vcs/subversion.txt
sc/__init__.py
sc.dev.core.egg-info/PKG-INFO
sc.dev.core.egg-info/SOURCES.txt
sc.dev.core.egg-info/dependency_links.txt
sc.dev.core.egg-info/entry_points.txt
sc.dev.core.egg-info/namespace_packages.txt
sc.dev.core.egg-info/not-zip-safe
sc.dev.core.egg-info/requires.txt
sc.dev.core.egg-info/top_level.txt
sc/dev/__init__.py
sc/dev/core/__init__.py
sc/dev/core/sphinx_pypi.py