Metadata-Version: 1.0
Name: sc.dev.core
Version: 20110707.01
Summary: Developement core packages used by Simples Consultoria
Home-page: http://www.simplesconsultoria.com.br
Author: Simples Consultoria
Author-email: products@simplesconsultoria.com.br
License: GPL
Keywords: plone development helpers
Platform: UNKNOWN
Classifier: Programming Language :: Python
